Metadata-Version: 2.1
Name: yaml2pyclass-mecher
Version: 0.1.8
Summary: Add option to choose final class in config
Home-page: https://github.com/MaximChernyak98/yaml2pyclass-mecher
Author: Alexander Naumann, Felix Hertlein
Author-email: Maksim Cherniak <maximchernyak98@gmail.com>
License: MIT
Classifier: Programming Language :: Python :: 3
Classifier: License :: OSI Approved :: MIT License
Classifier: Operating System :: OS Independent
Requires-Python: >=3.7.0
License-File: LICENSE
